distromax/__init__.py
distromax/analytical.py
distromax/fit.py
distromax/logging.py
distromax-1.2.3.dist-info/LICENSE.md
distromax-1.2.3.dist-info/METADATA
distromax-1.2.3.dist-info/WHEEL
distromax-1.2.3.dist-info/top_level.txt
distromax-1.2.3.dist-info/RECORD
