Metadata-Version: 2.1
Name: distromax
Version: 1.2.3
Summary: Empirically estimating the distribution of the loudest candidate from a gravitational-wave search.
License: MIT License
Project-URL: Source, https://github.com/Rodrigo-Tenorio/distromax
Project-URL: Issue tracker, https://github.com/Rodrigo-Tenorio/distromax/issues
Classifier: Programming Language :: Python :: 3
Classifier: License :: OSI Approved :: MIT License
Classifier: Operating System :: OS Independent
Classifier: Natural Language :: English
Classifier: Intended Audience :: Science/Research
Requires-Python: >=3.9
License-File: LICENSE.md
Requires-Dist: numpy
Requires-Dist: scipy
Requires-Dist: scikit-image
Requires-Dist: tqdm
Provides-Extra: examples
Requires-Dist: matplotlib; extra == "examples"
Provides-Extra: tests
Requires-Dist: black; extra == "tests"
Requires-Dist: flaky; extra == "tests"
Requires-Dist: pytest; extra == "tests"
